LICENSE
MANIFEST.in
README.md
pyproject.toml
setup.cfg
setup.py
src/napari_calibration/Image_widget.py
src/napari_calibration/__init__.py
src/napari_calibration/calibration_widget.py
src/napari_calibration/constant.py
src/napari_calibration/napari.yaml
src/napari_calibration.egg-info/PKG-INFO
src/napari_calibration.egg-info/SOURCES.txt
src/napari_calibration.egg-info/dependency_links.txt
src/napari_calibration.egg-info/entry_points.txt
src/napari_calibration.egg-info/requires.txt
src/napari_calibration.egg-info/top_level.txt
src/napari_calibration/_tests/__init__.py
src/napari_calibration/_tests/test_dock_widget.py
src/napari_calibration/_tests/test_reader.py
src/napari_calibration/_tests/test_sample_data.py
src/napari_calibration/_tests/test_widget.py
src/napari_calibration/_tests/test_writer.py
src/napari_calibration/logo/logo_ids.jpg
src/napari_calibration/styles/widget_live.css