Metadata-Version: 2.1
Name: napari-calibration
Version: 0.0.14
Summary: Plug in which enables to make camera calibration
Home-page: https://github.com/tcotte/napari-calibration
Author: Tristan Cotte
Author-email: tristan.cotte@sgs.com
License: BSD-3-Clause
Project-URL: Bug Tracker, https://github.com/tcotte/napari-calibration/issues
Project-URL: Documentation, https://github.com/tcotte/napari-calibration#README.md
Project-URL: Source Code, https://github.com/tcotte/napari-calibration
Project-URL: User Support, https://github.com/tcotte/napari-calibration/issues
Platform: UNKNOWN
Classifier: Development Status :: 2 - Pre-Alpha
Classifier: Intended Audience :: Developers
Classifier: Framework :: napari
Classifier: Topic :: Software Development :: Testing
Classifier: Programming Language :: Python
Classifier: Programming Language :: Python :: 3
Classifier: Programming Language :: Python :: 3.7
Classifier: Programming Language :: Python :: 3.8
Classifier: Programming Language :: Python :: 3.9
Classifier: Programming Language :: Python :: 3.10
Classifier: Operating System :: OS Independent
Classifier: License :: OSI Approved :: BSD License
Requires-Python: >=3.7
License-File: LICENSE
